jumpstarter_driver_iscsi/__init__.py
jumpstarter_driver_iscsi/client.py
jumpstarter_driver_iscsi/driver.py
jumpstarter_driver_iscsi/py.typed
jumpstarter_driver_iscsi-0.7.4.dist-info/METADATA
jumpstarter_driver_iscsi-0.7.4.dist-info/WHEEL
jumpstarter_driver_iscsi-0.7.4.dist-info/RECORD
