Metadata-Version: 2.4
Name: jumpstarter-driver-iscsi
Version: 0.7.4
Summary: Exporter ISCSI service driver
Project-URL: Homepage, https://jumpstarter.dev
Project-URL: source_archive, https://github.com/jumpstarter-dev/repo/archive/c5d38de69eadbb8eb0388bcfe3430a679fff0059.zip
Author-email: Benny Zlotnik <bzlotnik@redhat.com>
Requires-Python: >=3.11
Requires-Dist: anyio>=4.10.0
Requires-Dist: jumpstarter
Requires-Dist: jumpstarter-driver-composite
Requires-Dist: jumpstarter-driver-opendal
Requires-Dist: rtslib-fb
